mb_pandas/__init__.py
mb_pandas/aio.py
mb_pandas/convert_data.py
mb_pandas/dfload.py
mb_pandas/profiler.py
mb_pandas/transform.py
mb_pandas/version.py
mb_pandas-20230211.post57.data/scripts/df_profile
mb_pandas-20230211.post57.data/scripts/df_view
mb_pandas-20230211.post57.dist-info/METADATA
mb_pandas-20230211.post57.dist-info/WHEEL
mb_pandas-20230211.post57.dist-info/top_level.txt
mb_pandas-20230211.post57.dist-info/RECORD
