Metadata-Version: 2.1
Name: mb_pandas
Version: 20230211.post57
Summary: Basic Pandas functions packag
Author: ['Malav Bateriwala']
Requires-Python: >=3.8
